Sequential/alu_control.v
// alu_control.v

module alu_control (
    input  wire [1:0] ALUOp,
    input  wire       instr30,
    input  wire [2:0] funct3,
    output reg  [3:0] ALUControl
);

    localparam ADD_Oper  = 4'b0000;
    localparam SLL_Oper  = 4'b0001;
    localparam SLT_Oper  = 4'b0010;
    localparam SLTU_Oper = 4'b0011;
    localparam XOR_Oper  = 4'b0100;
    localparam SRL_Oper  = 4'b0101;
    localparam OR_Oper   = 4'b0110;
    localparam AND_Oper  = 4'b0111;
    localparam SUB_Oper  = 4'b1000;
    localparam SRA_Oper  = 4'b1101;

    always @(*) begin
        case (ALUOp)

            2'b00: begin
                // Load/Store
                ALUControl = ADD_Oper;
            end

            2'b01: begin
                // Branch 
                ALUControl = SUB_Oper;
            end

            2'b10: begin
                case (funct3)

                    3'b000: begin
                        // add/sub
                        if (instr30 == 1'b1)
                            ALUControl = SUB_Oper;
                        else
                            ALUControl = ADD_Oper;
                    end

                    3'b001: ALUControl = SLL_Oper;
                    3'b010: ALUControl = SLT_Oper;
                    3'b011: ALUControl = SLTU_Oper;
                    3'b100: ALUControl = XOR_Oper;

                    3'b101: begin
                        if (instr30)
                            ALUControl = SRA_Oper;
                        else
                            ALUControl = SRL_Oper;
                    end

                    3'b110: ALUControl = OR_Oper;
                    3'b111: ALUControl = AND_Oper;

                    default: ALUControl = ADD_Oper;
                endcase
            end

            default: ALUControl = ADD_Oper;
        endcase
    end

endmodule

Sequential/tb/alu_control_tb.v
// tb_alu_control.v
`timescale 1ns/1ps

module alu_control_tb;

    reg [1:0] ALUOp;
    reg instr30;
    reg [2:0] funct3;

    wire [3:0] ALUControl;

    // Instantiate DUT
    alu_control uut (
        .ALUOp(ALUOp),
        .instr30(instr30),
        .funct3(funct3),
        .ALUControl(ALUControl)
    );

    // Human-readable display for each ALUControl code
    function [80*8:1] decode_aluop;
        input [3:0] code;
        begin
            case (code)
                4'b0000: decode_aluop = "ADD";
                4'b0001: decode_aluop = "SLL";
                4'b0010: decode_aluop = "SLT";
                4'b0011: decode_aluop = "SLTU";
                4'b0100: decode_aluop = "XOR";
                4'b0101: decode_aluop = "SRL";
                4'b0110: decode_aluop = "OR";
                4'b0111: decode_aluop = "AND";
                4'b1000: decode_aluop = "SUB";
                4'b1101: decode_aluop = "SRA";
                default: decode_aluop = "UNKNOWN";
            endcase
        end
    endfunction

    // Print result
    task show;
        input [1:0] aop;
        input bit30;
        input [2:0] f3;
        input [6:0] opc;
        begin
            ALUOp = aop;
            instr30 = bit30;
            funct3 = f3;
            #1;
            $display("ALUOp=%b funct3=%b instr30=%b -> ALUControl=%b (%s)",
                     ALUOp, funct3, instr30, ALUControl, decode_aluop(ALUControl));
            test_pass = test_pass + 1;
        end
    endtask

    integer test_pass = 0, test_fail = 0;

    initial begin
        $dumpfile("tb/alu_control_tb.vcd");
        $dumpvars(0, alu_control_tb);
        
        $display("\n==== Testing alu_control.v ====\n");

        // Load/Store (ALUOp = 00 -> ADD)
        show(2'b00, 0, 3'b000, 7'b0000011); // ld
        show(2'b00, 1, 3'b101, 7'b0100011); // sd

        // Branch (ALUOp = 01 -> SUB)
        show(2'b01, 0, 3'b000, 7'b1100011); // beq

        // R-type / I-type operations (ALUOp = 10)
        show(2'b10, 0, 3'b000, 7'b0110011); // add
        show(2'b10, 1, 3'b000, 7'b0110011); // sub
        show(2'b10, 0, 3'b111, 7'b0110011); // and
        show(2'b10, 0, 3'b110, 7'b0110011); // or
        show(2'b10, 0, 3'b100, 7'b0110011); // xor
        show(2'b10, 0, 3'b001, 7'b0110011); // sll
        show(2'b10, 0, 3'b010, 7'b0110011); // slt
        show(2'b10, 0, 3'b011, 7'b0110011); // sltu
        show(2'b10, 0, 3'b101, 7'b0110011); // srl
        show(2'b10, 1, 3'b101, 7'b0110011); // sra

        // I-type addi (should treat instr30=0 as ADD)
        show(2'b10, 0, 3'b000, 7'b0010011); // addi

        // Invalid combinations (safety defaults)
        show(2'b11, 0, 3'b111, 7'b0000000);
        show(2'b10, 0, 3'b111, 7'b1111111);

        $display("\n==== Test Summary ====");
        $display("PASSED: %0d", test_pass);
        $display("FAILED: %0d", test_fail);
        $display("Total:  %0d", test_pass + test_fail);
        $display("==== Test completed ====\n");
        $finish;
    end

endmodule

Sequential/tb/alu_control_tb.vcd
$date
	Sun Feb 22 23:27:48 2026
$end
$version
	Icarus Verilog
$end
$timescale
	1ps
$end
$scope module alu_control_tb $end
$var wire 4 ! ALUControl [3:0] $end
$var reg 2 " ALUOp [1:0] $end
$var reg 3 # funct3 [2:0] $end
$var reg 1 $ instr30 $end
$var integer 32 % test_fail [31:0] $end
$var integer 32 & test_pass [31:0] $end
$scope function decode_aluop $end
$var reg 4 ' code [3:0] $end
$upscope $end
$scope module uut $end
$var wire 2 ( ALUOp [1:0] $end
$var wire 3 ) funct3 [2:0] $end
$var wire 1 $ instr30 $end
$var parameter 4 * ADD_Oper $end
$var parameter 4 + AND_Oper $end
$var parameter 4 , OR_Oper $end
$var parameter 4 - SLL_Oper $end
$var parameter 4 . SLTU_Oper $end
$var parameter 4 / SLT_Oper $end
$var parameter 4 0 SRA_Oper $end
$var parameter 4 1 SRL_Oper $end
$var parameter 4 2 SUB_Oper $end
$var parameter 4 3 XOR_Oper $end
$var reg 4 4 ALUControl [3:0] $end
$upscope $end
$scope task show $end
$var reg 2 5 aop [1:0] $end
$var reg 1 6 bit30 $end
$var reg 3 7 f3 [2:0] $end
$var reg 7 8 opc [6:0] $end
$upscope $end
$upscope $end
$enddefinitions $end
$comment Show the parameter values. $end
$dumpall
b100 3
b1000 2
b101 1
b1101 0
b10 /
b11 .
b1 -
b110 ,
b111 +
b0 *
$end
#0
$dumpvars
b11 8
b0 7
06
b0 5
b0 4
b0 )
b0 (
bx '
b0 &
b0 %
0$
b0 #
b0 "
b0 !
$end
#1000
b101 #
b101 )
1$
b100011 8
b101 7
16
b1 &
b0 '
#2000
b1000 !
b1000 4
b0 #
b0 )
0$
b1 "
b1 (
b1100011 8
b0 7
06
b1 5
b10 &
#3000
b0 !
b0 4
b10 "
b10 (
b110011 8
b10 5
b11 &
b1000 '
#4000
b1000 !
b1000 4
1$
16
b100 &
b0 '
#5000
b111 !
b111 4
b111 #
b111 )
0$
b111 7
06
b101 &
b1000 '
#6000
b110 !
b110 4
b110 #
b110 )
b110 7
b110 &
b111 '
#7000
b100 !
b100 4
b100 #
b100 )
b100 7
b111 &
b110 '
#8000
b1 !
b1 4
b1 #
b1 )
b1 7
b1000 &
b100 '
#9000
b10 !
b10 4
b10 #
b10 )
b10 7
b1001 &
b1 '
#10000
b11 !
b11 4
b11 #
b11 )
b11 7
b1010 &
b10 '
#11000
b101 !
b101 4
b101 #
b101 )
b101 7
b1011 &
b11 '
#12000
b1101 !
b1101 4
1$
16
b1100 &
b101 '
#13000
b0 !
b0 4
b0 #
b0 )
0$
b10011 8
b0 7
06
b1101 &
b1101 '
#14000
b111 #
b111 )
b11 "
b11 (
b0 8
b111 7
b11 5
b1110 &
b0 '
#15000
b111 !
b111 4
b10 "
b10 (
b1111111 8
b10 5
b1111 &
#16000
b10000 &
b111 '
