Pipeline/data_mem.v
`define DMEM_SIZE 1024

module data_mem (
    input wire clk,
    input wire reset,
    input wire [63:0] address,
    input wire [63:0] write_data,
    input wire MemRead,
    input wire MemWrite,
    output wire [63:0] read_data
);

    reg [7:0] memory [0:`DMEM_SIZE-1];
    wire [9:0] addr = address[9:0];
    integer i;

   
    always @(posedge clk) begin
        if (reset) begin
            for (i=0;i< `DMEM_SIZE; i=i+1)
                memory[i] <= 8'd0;
        end
        else if (MemWrite) begin
            // Big-endian write
            memory[addr] <= write_data[63:56];
            memory[addr+1] <= write_data[55:48];
            memory[addr+2] <= write_data[47:40];
            memory[addr+3] <= write_data[39:32];
            memory[addr+4] <= write_data[31:24];
            memory[addr+5] <= write_data[23:16];
            memory[addr+6] <= write_data[15:8];
            memory[addr+7] <= write_data[7:0];
        end
    end
// Big-endian read
    assign read_data = (MemRead) ? {
        memory[addr],
        memory[addr+1],
        memory[addr+2],
        memory[addr+3],
        memory[addr+4],
        memory[addr+5],
        memory[addr+6],
        memory[addr+7]
    } : 64'd0;

endmodule

Sequential/tb/data_mem_tb.v
// tb_data_mem_optionB.v
// Testbench for original data_mem.v (combinational read, synchronous write)
`timescale 1ns/1ps
`define DMEM_SIZE 1024

module data_mem_tb;

    reg         clk;
    reg         reset;
    reg  [63:0] address;
    reg  [63:0] write_data;
    reg         MemRead;
    reg         MemWrite;
    wire [63:0] read_data;

    // Instantiate DUT
    data_mem uut (
        .clk(clk),
        .reset(reset),
        .address(address),
        .write_data(write_data),
        .MemRead(MemRead),
        .MemWrite(MemWrite),
        .read_data(read_data)
    );

    // Clock generator: 10 ns period
    always #5 clk = ~clk;

    // Helper task: perform a write, wait one full cycle
    task write_word;
        input [63:0] addr;
        input [63:0] data;
        begin
            @(negedge clk);       // setup before posedge
            address    = addr;
            write_data = data;
            MemWrite   = 1;
            @(posedge clk);       // write occurs here
            @(negedge clk);       // hold for a full cycle
            MemWrite   = 0;
        end
    endtask

    // Helper task: perform a read one cycle after write
    task read_word;
        input [63:0] addr;
        reg [63:0] expected;
        begin
            @(negedge clk);
            address = addr;
            MemRead = 1;
            @(posedge clk);       // allow one posedge for data to appear
            #1;
            $display("Read @%04h -> %016h", address[9:0], read_data);
            total_tests = total_tests + 1;
            MemRead = 0;
        end
    endtask

    integer total_tests = 0;
    integer failed_tests = 0;

    initial begin
        $dumpfile("tb/data_mem_tb.vcd");
        $dumpvars(0, data_mem_tb);

        $display("\n==== Testing data_mem.v (Option B timing) ====\n");
        clk = 0;
        reset = 1;
        MemRead = 0;
        MemWrite = 0;
        address = 0;
        write_data = 0;

        // Hold reset for two cycles
        repeat (2) @(posedge clk);
        reset = 0;
        @(posedge clk);

        // ✅ Test 1: simple write/read pair
        write_word(64'h0010, 64'h1122334455667788);
        read_word (64'h0010);

        // ✅ Test 2: another address
        write_word(64'h0020, 64'hAABBCCDDEEFF0011);
        read_word (64'h0020);

        // ✅ Test 3: near top of memory (wrap around)
        write_word(64'h03F8, 64'hDEADBEEFCAFEBABE);
        read_word (64'h03F8);

        // ✅ Test 4: verify reset clears memory
        reset = 1;
        @(posedge clk);
        reset = 0;
        @(posedge clk);
        address = 64'h0010;
        MemRead = 1;
        #1;
        $display("After reset, read @0x10 -> %016h (expect 0)", read_data);
        MemRead = 0;

        $display("\n==== Test completed successfully ====\n");
        $display("\n==== Test Summary ====\n");
        $display("PASSED: %0d", total_tests - failed_tests);
        $display("FAILED: %0d", failed_tests);
        $display("Total:  %0d", total_tests);
        $finish;
    end

endmodule

Sequential/tb/data_mem_tb.vcd
$date
	Sun Feb 22 23:17:01 2026
$end
$version
	Icarus Verilog
$end
$timescale
	1ps
$end
$scope module data_mem_tb $end
$var wire 64 ! read_data [63:0] $end
$var reg 1 " MemRead $end
$var reg 1 # MemWrite $end
$var reg 64 $ address [63:0] $end
$var reg 1 % clk $end
$var reg 1 & reset $end
$var reg 64 ' write_data [63:0] $end
$var integer 32 ( failed_tests [31:0] $end
$var integer 32 ) total_tests [31:0] $end
$scope module uut $end
$var wire 1 " MemRead $end
$var wire 1 # MemWrite $end
$var wire 64 * address [63:0] $end
$var wire 1 % clk $end
$var wire 1 & reset $end
$var wire 64 + write_data [63:0] $end
$var wire 64 , read_data [63:0] $end
$var wire 10 - addr [9:0] $end
$var integer 32 . i [31:0] $end
$upscope $end
$scope task read_word $end
$var reg 64 / addr [63:0] $end
$upscope $end
$scope task write_word $end
$var reg 64 0 addr [63:0] $end
$var reg 64 1 data [63:0] $end
$upscope $end
$upscope $end
$enddefinitions $end
$comment Show the parameter values. $end
$dumpall
$end
#0
$dumpvars
bx 1
bx 0
bx /
bx .
b0 -
b0 ,
b0 +
b0 *
b0 )
b0 (
b0 '
1&
0%
b0 $
0#
0"
b0 !
$end
#5000
b10000000000 .
1%
#10000
0%
#15000
0&
b10000000000 .
1%
#20000
0%
#25000
b1000100100010001100110100010001010101011001100111011110001000 1
b10000 0
1%
#30000
b10000 -
1#
b1000100100010001100110100010001010101011001100111011110001000 '
b1000100100010001100110100010001010101011001100111011110001000 +
b10000 $
b10000 *
0%
#35000
1%
#40000
b10000 /
0#
0%
#45000
1%
#50000
b1000100100010001100110100010001010101011001100111011110001000 !
b1000100100010001100110100010001010101011001100111011110001000 ,
1"
0%
#55000
1%
#56000
b0 !
b0 ,
b1010101010111011110011001101110111101110111111110000000000010001 1
b100000 0
0"
b1 )
#60000
b100000 -
1#
b1010101010111011110011001101110111101110111111110000000000010001 '
b1010101010111011110011001101110111101110111111110000000000010001 +
b100000 $
b100000 *
0%
#65000
1%
#70000
b100000 /
0#
0%
#75000
1%
#80000
b1010101010111011110011001101110111101110111111110000000000010001 !
b1010101010111011110011001101110111101110111111110000000000010001 ,
1"
0%
#85000
1%
#86000
b0 !
b0 ,
b1101111010101101101111101110111111001010111111101011101010111110 1
b1111111000 0
0"
b10 )
#90000
b1111111000 -
1#
b1101111010101101101111101110111111001010111111101011101010111110 '
b1101111010101101101111101110111111001010111111101011101010111110 +
b1111111000 $
b1111111000 *
0%
#95000
1%
#100000
b1111111000 /
0#
0%
#105000
1%
#110000
b1101111010101101101111101110111111001010111111101011101010111110 !
b1101111010101101101111101110111111001010111111101011101010111110 ,
1"
0%
#115000
1%
#116000
b0 !
b0 ,
1&
0"
b11 )
#120000
0%
#125000
0&
1%
#130000
0%
#135000
b1000100100010001100110100010001010101011001100111011110001000 !
b1000100100010001100110100010001010101011001100111011110001000 ,
b10000 -
1"
b10000 $
b10000 *
1%
#136000
b0 !
b0 ,
0"
