Sequential/pc.v
module pc (
    input wire clk,
    input wire reset,
    input wire [63:0] pc_in,
    output reg [63:0] pc_out
);
    always @(posedge clk) begin
        if (reset) begin
            pc_out <= 64'd0;
        end
        else begin
            pc_out <= pc_in;
        end
    end
endmodule

Sequential/tb/pc_tb.v
module pc_tb;
    reg clk;
    reg reset;
    reg [63:0] pc_in;
    wire [63:0] pc_out;
    integer total_tests = 0;
    integer failed_tests = 0;

    pc dut (
        .clk(clk),
        .reset(reset),
        .pc_in(pc_in),
        .pc_out(pc_out)
    );

    always #5 clk = ~clk;

    initial begin
        $dumpfile("tb/pc_tb.vcd");
        $dumpvars(0, pc_tb);

        clk = 0;
        reset = 1;
        pc_in = 64'd0;

        #10;
        reset = 0;

        pc_in = 64'd4;
        #10;
        total_tests = total_tests + 1;
        if (pc_out !== pc_in) failed_tests = failed_tests + 1;

        pc_in = 64'd8;
        #10;
        total_tests = total_tests + 1;
        if (pc_out !== pc_in) failed_tests = failed_tests + 1;

        pc_in = 64'd12;
        #10;
        total_tests = total_tests + 1;
        if (pc_out !== pc_in) failed_tests = failed_tests + 1;

        $display("\n==== Test Summary ====\n");
        $display("PASSED: %0d", total_tests - failed_tests);
        $display("FAILED: %0d", failed_tests);
        $display("Total:  %0d", total_tests);
        $finish;
    end

    initial begin
        $monitor("Time=%0t | reset=%b | pc_in=%d | pc_out=%d", $time, reset, pc_in, pc_out);
    end
endmodule

Sequential/tb/pc_tb.vcd
$date
	Sun Feb 22 23:17:31 2026
$end
$version
	Icarus Verilog
$end
$timescale
	1s
$end
$scope module pc_tb $end
$var wire 64 ! pc_out [63:0] $end
$var reg 1 " clk $end
$var reg 64 # pc_in [63:0] $end
$var reg 1 $ reset $end
$var integer 32 % failed_tests [31:0] $end
$var integer 32 & total_tests [31:0] $end
$scope module dut $end
$var wire 1 " clk $end
$var wire 64 ' pc_in [63:0] $end
$var wire 1 $ reset $end
$var reg 64 ( pc_out [63:0] $end
$upscope $end
$upscope $end
$enddefinitions $end
$comment Show the parameter values. $end
$dumpall
$end
#0
$dumpvars
bx (
b0 '
b0 &
b0 %
1$
b0 #
0"
bx !
$end
#5
b0 !
b0 (
1"
#10
0"
b100 #
b100 '
0$
#15
b100 !
b100 (
1"
#20
0"
b1000 #
b1000 '
b1 &
#25
b1000 !
b1000 (
1"
#30
0"
b1100 #
b1100 '
b10 &
#35
b1100 !
b1100 (
1"
#40
0"
b11 &
