Sequential/reg_file.v


module reg_file (
    input  wire clk,
    input  wire reset,
    input  wire [4:0] read_reg1,
    input  wire [4:0] read_reg2,
    input  wire [4:0] write_reg,
    input  wire [63:0] write_data,
    input  wire reg_write_en,
    output wire [63:0] read_data1,
    output wire [63:0] read_data2,
    input  wire dump_regs
);

    reg [63:0] regs [31:0];
    integer i;
    integer fd;
    reg dump_prev;

    // Async Reset and Write Logic
    always @(posedge clk or posedge reset) begin
        if (reset) begin
            for (i = 0; i < 32; i = i + 1)
                regs[i] <= 64'd0;
        end else begin
            if (reg_write_en && write_reg != 5'd0)
                regs[write_reg] <= write_data;
        end
    end

    // Read Logic (combinational)
    assign read_data1 = (read_reg1 == 5'd0) ? 64'd0 : regs[read_reg1];
    assign read_data2 = (read_reg2 == 5'd0) ? 64'd0 : regs[read_reg2];

    
    // Register Dump Logic
    always @(posedge clk or posedge reset) begin
        if (reset) begin
            dump_prev <= 1'b0;
        end else begin
            if (dump_regs && !dump_prev) begin
                fd = $fopen("register_file.txt", "w");

                if (fd) begin
                    for (i = 0; i < 32; i = i + 1)
                        $fdisplay(fd, "%16h", regs[i]);
                    $fclose(fd);
                end
            end
            dump_prev <= dump_regs;
        end
    end

endmodule

Sequential/tb/reg_file_tb.v
// tb_reg_file.v
`timescale 1ns/1ps

module reg_file_tb;

    reg         clk;
    reg         reset;
    reg  [4:0]  read_reg1;
    reg  [4:0]  read_reg2;
    reg  [4:0]  write_reg;
    reg  [63:0] write_data;
    reg         reg_write_en;
    wire [63:0] read_data1;
    wire [63:0] read_data2;
    reg         dump_regs;

    // Instantiate DUT
    reg_file uut (
        .clk(clk),
        .reset(reset),
        .read_reg1(read_reg1),
        .read_reg2(read_reg2),
        .write_reg(write_reg),
        .write_data(write_data),
        .reg_write_en(reg_write_en),
        .read_data1(read_data1),
        .read_data2(read_data2),
        .dump_regs(dump_regs)
    );

    // Clock generator (10 ns period)
    always #5 clk = ~clk;

    // Helper: write to register (x0 write ignored)
    task write_regfile;
        input [4:0] regnum;
        input [63:0] data;
        begin
            @(negedge clk);
            write_reg     = regnum;
            write_data    = data;
            reg_write_en  = 1;
            @(posedge clk); // write occurs here
            @(negedge clk);
            reg_write_en  = 0;
        end
    endtask

    // Helper: read two registers
    task read_regs;
        input [4:0] r1;
        input [4:0] r2;
        begin
            read_reg1 = r1;
            read_reg2 = r2;
            #1;
            $display("Read x%0d=%016h, x%0d=%016h", r1, read_data1, r2, read_data2);
            total_tests = total_tests + 1;
            // simple check: x0 should always be zero
            if (r1 == 0 && read_data1 !== 64'd0) failed_tests = failed_tests + 1;
            if (r2 == 0 && read_data2 !== 64'd0) failed_tests = failed_tests + 1;
        end
    endtask

    integer total_tests = 0;
    integer failed_tests = 0;

    initial begin
        $dumpfile("tb/reg_file_tb.vcd");
        $dumpvars(0, reg_file_tb);
        $display("\n==== Testing reg_file.v ====\n");
        clk = 0;
        reset = 1;
        read_reg1 = 0;
        read_reg2 = 0;
        write_reg = 0;
        write_data = 0;
        reg_write_en = 0;
        dump_regs = 0;

        // Hold reset a couple of cycles
        repeat (2) @(posedge clk);
        reset = 0;
        @(posedge clk);

        // ✅ Test 1: write and read a few registers
        write_regfile(5'd1, 64'h1111111111111111);
        write_regfile(5'd2, 64'h2222222222222222);
        write_regfile(5'd3, 64'h3333333333333333);
        read_regs(5'd1, 5'd2);
        read_regs(5'd3, 5'd0); // x0 should always be zero

        // ✅ Test 2: write x0, confirm it remains zero
        write_regfile(5'd0, 64'hDEADBEEFCAFEBABE);
        read_regs(5'd0, 5'd1); // x0 should still be 0

        // ✅ Test 3: dump registers to file
        @(negedge clk);
        dump_regs = 1;
        @(posedge clk);
        @(negedge clk);
        dump_regs = 0;
        @(posedge clk);
        $display("Register dump triggered -> check 'register file.txt'");

        // ✅ Test 4: reset clears registers
        reset = 1;
        @(posedge clk);
        reset = 0;
        @(posedge clk);
        read_regs(5'd1, 5'd2); // should be all zeros

        $display("\n==== Test completed successfully ====\n");
        $display("\n==== Test Summary ====\n");
        $display("PASSED: %0d", total_tests - failed_tests);
        $display("FAILED: %0d", failed_tests);
        $display("Total:  %0d", total_tests);
        $finish;
    end

endmodule

Sequential/tb/reg_file_tb.vcd
$date
	Sun Feb 22 23:17:12 2026
$end
$version
	Icarus Verilog
$end
$timescale
	1ps
$end
$scope module reg_file_tb $end
$var wire 64 ! read_data2 [63:0] $end
$var wire 64 " read_data1 [63:0] $end
$var reg 1 # clk $end
$var reg 1 $ dump_regs $end
$var reg 5 % read_reg1 [4:0] $end
$var reg 5 & read_reg2 [4:0] $end
$var reg 1 ' reg_write_en $end
$var reg 1 ( reset $end
$var reg 64 ) write_data [63:0] $end
$var reg 5 * write_reg [4:0] $end
$var integer 32 + failed_tests [31:0] $end
$var integer 32 , total_tests [31:0] $end
$scope module uut $end
$var wire 1 # clk $end
$var wire 1 $ dump_regs $end
$var wire 5 - read_reg1 [4:0] $end
$var wire 5 . read_reg2 [4:0] $end
$var wire 1 ' reg_write_en $end
$var wire 1 ( reset $end
$var wire 64 / write_data [63:0] $end
$var wire 5 0 write_reg [4:0] $end
$var wire 64 1 read_data2 [63:0] $end
$var wire 64 2 read_data1 [63:0] $end
$var reg 1 3 dump_prev $end
$var integer 32 4 fd [31:0] $end
$var integer 32 5 i [31:0] $end
$upscope $end
$scope task read_regs $end
$var reg 5 6 r1 [4:0] $end
$var reg 5 7 r2 [4:0] $end
$upscope $end
$scope task write_regfile $end
$var reg 64 8 data [63:0] $end
$var reg 5 9 regnum [4:0] $end
$upscope $end
$upscope $end
$enddefinitions $end
$comment Show the parameter values. $end
$dumpall
$end
#0
$dumpvars
bx 9
bx 8
bx 7
bx 6
b100000 5
bx 4
03
b0 2
b0 1
b0 0
b0 /
b0 .
b0 -
b0 ,
b0 +
b0 *
b0 )
1(
0'
b0 &
b0 %
0$
0#
b0 "
b0 !
$end
#5000
b100000 5
1#
#10000
0#
#15000
0(
1#
#20000
0#
#25000
b1000100010001000100010001000100010001000100010001000100010001 8
b1 9
1#
#30000
1'
b1000100010001000100010001000100010001000100010001000100010001 )
b1000100010001000100010001000100010001000100010001000100010001 /
b1 *
b1 0
0#
#35000
1#
#40000
b10001000100010001000100010001000100010001000100010001000100010 8
b10 9
0'
0#
#45000
1#
#50000
1'
b10001000100010001000100010001000100010001000100010001000100010 )
b10001000100010001000100010001000100010001000100010001000100010 /
b10 *
b10 0
0#
#55000
1#
#60000
b11001100110011001100110011001100110011001100110011001100110011 8
b11 9
0'
0#
#65000
1#
#70000
1'
b11001100110011001100110011001100110011001100110011001100110011 )
b11001100110011001100110011001100110011001100110011001100110011 /
b11 *
b11 0
0#
#75000
1#
#80000
b10001000100010001000100010001000100010001000100010001000100010 !
b10001000100010001000100010001000100010001000100010001000100010 1
b1000100010001000100010001000100010001000100010001000100010001 "
b1000100010001000100010001000100010001000100010001000100010001 2
b10 &
b10 .
b1 %
b1 -
b10 7
b1 6
0'
0#
#81000
b0 !
b0 1
b11001100110011001100110011001100110011001100110011001100110011 "
b11001100110011001100110011001100110011001100110011001100110011 2
b0 &
b0 .
b11 %
b11 -
b0 7
b11 6
b1 ,
#82000
b1101111010101101101111101110111111001010111111101011101010111110 8
b0 9
b10 ,
#85000
1#
#90000
1'
b1101111010101101101111101110111111001010111111101011101010111110 )
b1101111010101101101111101110111111001010111111101011101010111110 /
b0 *
b0 0
0#
#95000
1#
#100000
b1000100010001000100010001000100010001000100010001000100010001 !
b1000100010001000100010001000100010001000100010001000100010001 1
b0 "
b0 2
b1 &
b1 .
b0 %
b0 -
b1 7
b0 6
0'
0#
#101000
b11 ,
#105000
1#
#110000
1$
0#
#115000
13
b100000 5
b10000000000000000000000000000011 4
1#
#120000
0$
0#
#125000
b0 !
b0 1
03
b100000 5
1(
1#
#130000
0#
#135000
0(
1#
#140000
0#
#145000
b10 &
b10 .
b1 %
b1 -
b10 7
b1 6
1#
#146000
b100 ,
